datasette_build/__init__.py
datasette_build/cli.py
datasette_build/core.py
datasette_build/datasette_plugin.py
datasette_build/default_formats.py
datasette_build/hookspecs.py
datasette_build/sqlite_utils_plugin.py
datasette_build-0.1a0.dist-info/LICENSE
datasette_build-0.1a0.dist-info/METADATA
datasette_build-0.1a0.dist-info/WHEEL
datasette_build-0.1a0.dist-info/entry_points.txt
datasette_build-0.1a0.dist-info/top_level.txt
datasette_build-0.1a0.dist-info/RECORD
