Metadata-Version: 2.1
Name: datasette-build
Version: 0.1a0
Summary: Build a directory full of files into a SQLite database
Author: Datasette
License: Apache-2.0
Project-URL: Homepage, https://github.com/datasette/datasette-build
Project-URL: Changelog, https://github.com/datasette/datasette-build/releases
Project-URL: Issues, https://github.com/datasette/datasette-build/issues
Project-URL: CI, https://github.com/datasette/datasette-build/actions
Classifier: Framework :: Datasette
Classifier: License :: OSI Approved :: Apache Software License
Requires-Python: >=3.8
License-File: LICENSE
Requires-Dist: click
Requires-Dist: sqlite-utils
Requires-Dist: PyYAML
Requires-Dist: pluggy
Provides-Extra: datasette
Requires-Dist: datasette ; extra == 'datasette'
Provides-Extra: test
Requires-Dist: pytest ; extra == 'test'
Requires-Dist: pytest-asyncio ; extra == 'test'
